hydras/__init__.py
hydras/array.py
hydras/base.py
hydras/enum.py
hydras/scalars.py
hydras/struct.py
hydras/utils.py
hydras/validators.py
hydras/tools/__init__.py
hydras/tools/dwarf2hydra.py
tests/__init__.py
tests/test_array.py
tests/test_array_vla.py
tests/test_enum.py
tests/test_scalar.py
tests/test_settings.py
tests/test_struct.py
tests/test_validation.py
tests/utils.py
Hydras-3.1.2.dist-info/LICENSE
Hydras-3.1.2.dist-info/METADATA
Hydras-3.1.2.dist-info/WHEEL
Hydras-3.1.2.dist-info/entry_points.txt
Hydras-3.1.2.dist-info/top_level.txt
Hydras-3.1.2.dist-info/RECORD
