Metadata-Version: 2.1
Name: Hydras
Version: 3.1.2
Summary: A module for constructions of structured binary packets.
Home-page: https://github.com/Gilnaa/Hydras
Author: Gilad Naaman
Author-email: gilad@naaman.io
License: UNKNOWN
Platform: UNKNOWN
Classifier: Programming Language :: Python :: 3
Classifier: License :: OSI Approved :: MIT License
Classifier: Operating System :: OS Independent
Requires-Dist: pyelftools
